pln/__init__.py
pln/core.py
pln-0.0.2dev.dist-info/DESCRIPTION.rst
pln-0.0.2dev.dist-info/METADATA
pln-0.0.2dev.dist-info/metadata.json
pln-0.0.2dev.dist-info/RECORD
pln-0.0.2dev.dist-info/top_level.txt
pln-0.0.2dev.dist-info/WHEEL
